CHANGES.rst
MANIFEST.in
README.rst
setup.py
django_memcached_pool_gto.egg-info/PKG-INFO
django_memcached_pool_gto.egg-info/SOURCES.txt
django_memcached_pool_gto.egg-info/dependency_links.txt
django_memcached_pool_gto.egg-info/not-zip-safe
django_memcached_pool_gto.egg-info/requires.txt
django_memcached_pool_gto.egg-info/top_level.txt
memcachepool/__init__.py
memcachepool/cache.py
memcachepool/client.py
memcachepool/pool.py
memcachepool/tests/__init__.py
memcachepool/tests/settings.py
memcachepool/tests/test_cache.py