Metadata-Version: 1.1
Name: django-memcached-pool-gto
Version: 0.6
Summary: A Memcached Pool for Django
Home-page: https://github.com/gto-web/django-memcached-pool
Author: Mozilla Services, GTO Web
Author-email: xiech@garena.com
License: UNKNOWN
Keywords: django memcached pool
Platform: UNKNOWN
Classifier: Programming Language :: Python
Classifier: Framework :: Pylons
Classifier: Topic :: Internet :: WWW/HTTP
Classifier: Topic :: Internet :: WWW/HTTP :: WSGI :: Application
Classifier: License :: OSI Approved :: Apache Software License
